MANIFEST.in
README.txt
__init__.py
manage.py
settings.py
setup.py
urls.py
django_migrate_mail.egg-info/PKG-INFO
django_migrate_mail.egg-info/SOURCES.txt
django_migrate_mail.egg-info/dependency_links.txt
django_migrate_mail.egg-info/not-zip-safe
django_migrate_mail.egg-info/requires.txt
django_migrate_mail.egg-info/top_level.txt
la_facebook/__init__.py
la_facebook/access.py
la_facebook/admin.py
la_facebook/exceptions.py
la_facebook/la_fb_logging.py
la_facebook/models.py
la_facebook/urls.py
la_facebook/views.py
la_facebook/callbacks/__init__.py
la_facebook/callbacks/base.py
la_facebook/callbacks/default.py
la_facebook/templatetags/__init__.py
la_facebook/templatetags/la_facebook_tags.py
la_facebook/tests/__init__.py
la_facebook/tests/test_access_module.py
la_facebook/tests/test_callbacks.py
la_facebook/tests/test_models.py
la_facebook/tests/test_views.py
la_facebook/tests/urls.py
la_facebook/tests/views.py
la_facebook/utils/__init__.py
la_facebook/utils/anyetree.py
la_facebook/utils/loader.py
migrate_mail/__init__.py
migrate_mail/forms.py
migrate_mail/models.py
migrate_mail/urls.py
migrate_mail/views.py
migrate_mail/migrations/0001_initial.py
migrate_mail/migrations/0002_auto__add_field_migration_domain__add_field_migration_admin_username__.py
migrate_mail/migrations/0003_auto__add_unique_label_migration_uid__add_field_migration_labels_proce.py
migrate_mail/migrations/0004_auto__add_field_migration_auth_token.py
migrate_mail/migrations/0005_auto__add_field_migration_messages_cnt.py
migrate_mail/migrations/0006_auto__del_field_label_labels__add_field_label_label__del_unique_label_.py
migrate_mail/migrations/0007_auto__add_field_migration_last_uid.py
migrate_mail/migrations/0008_auto.py
migrate_mail/migrations/0009_auto__del_unique_migration_to_username_from_email.py
migrate_mail/migrations/__init__.py
migrate_mail/static/accept.png
migrate_mail/static/ajax-loader.gif
migrate_mail/static/altbutton.gif
migrate_mail/static/altheaderbox.png
migrate_mail/static/altheadertab.png
migrate_mail/static/bg.png
migrate_mail/static/black.css
migrate_mail/static/button.gif
migrate_mail/static/container.gif
migrate_mail/static/cross_octagon.png
migrate_mail/static/exclamation.png
migrate_mail/static/exclamation_octagon_fram.png
