Metadata-Version: 1.0
Name: django-migrate-mail
Version: 0.2.1
Summary: Copy Gmail messages to another Gmail account.
Home-page: http://bitbucket.org/msayapin/gmailcopy
Author: Mikhail Sayapin
Author-email: mikhail.sayapin@gmail.com
License: UNKNOWN
Platform: UNKNOWN
